{
  "run_id": "zai-coding-plan-glm-4.7_pseudocode_task1_rep5",
  "model": "zai-coding-plan/glm-4.7",
  "condition": "pseudocode",
  "task": "1",
  "task_complexity": "simple",
  "domain": "dockerfile",
  "rep": 5,
  "timestamp": "2026-02-21T07:58:20+00:00",
  "duration_ms": 32628,
  "cli_tool": "opencode",
  "raw_output": "{\"type\":\"step_start\",\"timestamp\":1771660673087,\"sessionID\":\"ses_380cb90daffe5s35Rzw101Nw39\",\"part\":{\"id\":\"prt_c7f34803d001U4dLRGDS6uEOxv\",\"sessionID\":\"ses_380cb90daffe5s35Rzw101Nw39\",\"messageID\":\"msg_c7f346f67001vVy5xz4CHkvicB\",\"type\":\"step-start\",\"snapshot\":\"e29186b4ef5a75f56ad26be291900ddbdb5dee3f\"}}\n{\"type\":\"text\",\"timestamp\":1771660700607,\"sessionID\":\"ses_380cb90daffe5s35Rzw101Nw39\",\"part\":{\"id\":\"prt_c7f34d3630019oRTtDWrAck63m\",\"sessionID\":\"ses_380cb90daffe5s35Rzw101Nw39\",\"messageID\":\"msg_c7f346f67001vVy5xz4CHkvicB\",\"type\":\"text\",\"text\":\"```dockerfile\\n# Build stage\\nFROM maven:3.9.9-eclipse-temurin-21-alpine AS builder\\n\\nWORKDIR /build\\n\\nCOPY pom.xml .\\n\\nRUN mvn dependency:go-offline -B --no-transfer-progress\\n\\nCOPY . .\\n\\nRUN mvn clean package -DskipTests -B --no-transfer-progress && \\\\\\n    mv target/*.jar /app.jar\\n\\n# Runtime stage\\nFROM eclipse-temurin:21-jre-alpine\\n\\nRUN apk update && \\\\\\n    apk add --no-cache curl fontconfig ttf-dejavu && \\\\\\n    rm -rf /var/cache/apk/*\\n\\nRUN apk add --no-cache openjdk-17-jre-base openssl\\n\\nRUN keytool -importcert -keystore $JAVA_HOME/lib/security/cacerts -storepass changeit -noprompt \\\\\\n        -alias aws-rds-ca -file <(openssl s_client -connect rds.amazonaws.com:443 -servername rds.amazonaws.com 2>/dev/null | openssl x509) && \\\\\\n    keytool -importcert -keystore $JAVA_HOME/lib/security/cacerts -storepass changeit -noprompt \\\\\\n        -alias azure-digicert-root -file <(curl -s https://cacerts.digicert.com/DigiCertGlobalRootCA.crt)\\n\\nRUN addgroup -g 1001 -S app && \\\\\\n    adduser -u 1001 -S -G app app\\n\\nWORKDIR /app\\n\\nCOPY --from=builder --chown=app:app /app.jar /app/app.jar\\n\\nLABEL maintainer=\\\"your-email@example.com\\\" \\\\\\n      version=\\\"1.0.0\\\" \\\\\\n      description=\\\"Java analytics dashboard\\\"\\n\\nEXPOSE 3000\\n\\nHEALTHCHECK --interval=30s --timeout=3s --start-period=5s --retries=3 \\\\\\n    CMD curl -f http://localhost:3000/api/health || exit 1\\n\\nUSER app\\n\\nCMD [\\\"java\\\", \\\"-jar\\\", \\\"/app/app.jar\\\"]\\n```\",\"time\":{\"start\":1771660700606,\"end\":1771660700606}}}\n{\"type\":\"step_finish\",\"timestamp\":1771660700617,\"sessionID\":\"ses_380cb90daffe5s35Rzw101Nw39\",\"part\":{\"id\":\"prt_c7f34ebc0001Gv3rgHYmKooDf5\",\"sessionID\":\"ses_380cb90daffe5s35Rzw101Nw39\",\"messageID\":\"msg_c7f346f67001vVy5xz4CHkvicB\",\"type\":\"step-finish\",\"reason\":\"stop\",\"snapshot\":\"174e16854e23ee2140c803af3898097111b87e58\",\"cost\":0,\"tokens\":{\"total\":21053,\"input\":11058,\"output\":1579,\"reasoning\":1158,\"cache\":{\"read\":8416,\"write\":0}}}}"
}
