{
  "run_id": "zai-coding-plan-glm-4.7_markdown-target_task3_rep1",
  "model": "zai-coding-plan/glm-4.7",
  "condition": "markdown+target",
  "task": "3",
  "task_complexity": "medium",
  "domain": "sql-query",
  "rep": 1,
  "timestamp": "2026-02-22T15:15:47+00:00",
  "duration_ms": 19895,
  "cli_tool": "opencode",
  "raw_output": "{\"type\":\"step_start\",\"timestamp\":1771773334238,\"sessionID\":\"ses_37a148414ffeCQF7R2suIY4u1h\",\"part\":{\"id\":\"prt_c85eb92dd0011Lk280LcTq5Guj\",\"sessionID\":\"ses_37a148414ffeCQF7R2suIY4u1h\",\"messageID\":\"msg_c85eb7c200017496BJfLXnl2A8\",\"type\":\"step-start\",\"snapshot\":\"06988d0736fe190ecfe25d4af4df75208714b14f\"}}\n{\"type\":\"text\",\"timestamp\":1771773347613,\"sessionID\":\"ses_37a148414ffeCQF7R2suIY4u1h\",\"part\":{\"id\":\"prt_c85ebad25001MmOhYFdI5KlU29\",\"sessionID\":\"ses_37a148414ffeCQF7R2suIY4u1h\",\"messageID\":\"msg_c85eb7c200017496BJfLXnl2A8\",\"type\":\"text\",\"text\":\"```sql\\n-- models/staging/stg_orders.sql\\nWITH source AS (\\n    SELECT\\n        order_id,\\n        customer_id,\\n        order_date,\\n        status\\n    FROM {{ source('raw', 'orders') }}\\n)\\nSELECT\\n    order_id,\\n    customer_id,\\n    order_date,\\n    status\\nFROM source\\n```\\n\\n```sql\\n-- models/staging/stg_order_items.sql\\nWITH source AS (\\n    SELECT\\n        item_id,\\n        order_id,\\n        product_id,\\n        quantity,\\n        unit_price\\n    FROM {{ source('raw', 'order_items') }}\\n)\\nSELECT\\n    item_id,\\n    order_id,\\n    product_id,\\n    quantity,\\n    unit_price\\nFROM source\\n```\\n\\n```sql\\n-- models/staging/stg_products.sql\\nWITH source AS (\\n    SELECT\\n        product_id,\\n        name,\\n        category_id\\n    FROM {{ source('raw', 'products') }}\\n)\\nSELECT\\n    product_id,\\n    name,\\n    category_id\\nFROM source\\n```\\n\\n```sql\\n-- models/staging/stg_categories.sql\\nWITH source AS (\\n    SELECT\\n        category_id,\\n        name\\n    FROM {{ source('raw', 'categories') }}\\n)\\nSELECT\\n    category_id,\\n    name\\nFROM source\\n```\\n\\n```sql\\n-- models/staging/stg_returns.sql\\nWITH source AS (\\n    SELECT\\n        return_id,\\n        item_id,\\n        return_date,\\n        reason,\\n        status\\n    FROM {{ source('raw', 'returns') }}\\n)\\nSELECT\\n    return_id,\\n    item_id,\\n    return_date,\\n    reason,\\n    status\\nFROM source\\n```\\n\\n```sql\\n-- models/intermediate/int_deduped_returns.sql\\n-- Deduplicate returns to one approved return per item\\nWITH source AS (\\n    SELECT\\n        return_id,\\n        item_id,\\n        return_date,\\n        reason,\\n        status,\\n        ROW_NUMBER() OVER (\\n            PARTITION BY item_id\\n            ORDER BY return_date ASC\\n        ) AS row_num\\n    FROM {{ ref('stg_returns') }}\\n)\\nSELECT\\n    return_id,\\n    item_id,\\n    return_date,\\n    reason,\\n    status\\nFROM source\\nWHERE row_num = 1\\n```\\n\\n```sql\\n-- models/fact/fct_return_rates_by_category.sql\\n-- Calculate product return rates by category\\nWITH source AS (\\n    SELECT\\n        COALESCE(c.name, '(unknown)') AS category_name,\\n        COUNT(DISTINCT oi.item_id) AS total_items_sold,\\n        COUNT(DISTINCT r.item_id) AS total_items_returned,\\n        CAST(COUNT(DISTINCT r.item_id) AS DECIMAL(10,2)) / NULLIF(COUNT(DISTINCT oi.item_id), 0) AS return_rate\\n    FROM {{ ref('stg_order_items') }} oi\\n    LEFT JOIN {{ ref('stg_products') }} p\\n        ON p.product_id = oi.product_id\\n    LEFT JOIN {{ ref('stg_categories') }} c\\n        ON c.category_id = p.category_id\\n    LEFT JOIN {{ ref('int_deduped_returns') }} r\\n        ON r.item_id = oi.item_id\\n    GROUP BY\\n        COALESCE(c.name, '(unknown)')\\n)\\nSELECT\\n    category_name,\\n    total_items_sold,\\n    total_items_returned,\\n    return_rate\\nFROM source\\n```\",\"time\":{\"start\":1771773347613,\"end\":1771773347613}}}\n{\"type\":\"step_finish\",\"timestamp\":1771773347626,\"sessionID\":\"ses_37a148414ffeCQF7R2suIY4u1h\",\"part\":{\"id\":\"prt_c85ebc71e001S8hwNsnubYYtuT\",\"sessionID\":\"ses_37a148414ffeCQF7R2suIY4u1h\",\"messageID\":\"msg_c85eb7c200017496BJfLXnl2A8\",\"type\":\"step-finish\",\"reason\":\"stop\",\"snapshot\":\"06988d0736fe190ecfe25d4af4df75208714b14f\",\"cost\":0,\"tokens\":{\"total\":14843,\"input\":365,\"output\":1188,\"reasoning\":496,\"cache\":{\"read\":13290,\"write\":0}}}}"
}
